[
  {
    "modes": 2,
    "squeezing": 0.3,
    "shots": 200,
    "kl_gauss": 2.106173386708342,
    "kl_fock": 7.771561172104081e-27
  },
  {
    "modes": 2,
    "squeezing": 0.6,
    "shots": 200,
    "kl_gauss": 6.768357378884319,
    "kl_fock": 0.0
  },
  {
    "modes": 2,
    "squeezing": 0.9,
    "shots": 200,
    "kl_gauss": 11.190429272753107,
    "kl_fock": 7.771561172104081e-27
  },
  {
    "modes": 3,
    "squeezing": 0.3,
    "shots": 200,
    "kl_gauss": 3.2130653176068966,
    "kl_fock": 0.0
  },
  {
    "modes": 3,
    "squeezing": 0.6,
    "shots": 200,
    "kl_gauss": 9.957624336316412,
    "kl_fock": 0.0
  },
  {
    "modes": 3,
    "squeezing": 0.9,
    "shots": 200,
    "kl_gauss": 16.83156295221375,
    "kl_fock": 0.0
  },
  {
    "modes": 4,
    "squeezing": 0.3,
    "shots": 200,
    "kl_gauss": 3.8503318544196,
    "kl_fock": 0.0
  },
  {
    "modes": 4,
    "squeezing": 0.6,
    "shots": 200,
    "kl_gauss": 13.250150232413377,
    "kl_fock": 0.0
  },
  {
    "modes": 4,
    "squeezing": 0.9,
    "shots": 200,
    "kl_gauss": 19.063781745856904,
    "kl_fock": 2.8754776300554083e-25
  }
]
